{
    "arxiv_id": "1612.09268",
    "title": "The ontogeny of discourse structure mimics the development of literature",
    "authors": [
        {
            "name": "NB Mota",
            "citations_all": 3042,
            "citations_recent": 2418,
            "h_index_all": 24,
            "h_index_recent": 23,
            "i10_index_all": 38,
            "i10_index_recent": 35
        },
        {
            "name": "S Pinheiro",
            "citations_all": 33,
            "citations_recent": 27,
            "h_index_all": 3,
            "h_index_recent": 3,
            "i10_index_all": 1,
            "i10_index_recent": 1
        },
        {
            "name": "M Sigman",
            "citations_all": 23596,
            "citations_recent": 11260,
            "h_index_all": 76,
            "h_index_recent": 57,
            "i10_index_all": 186,
            "i10_index_recent": 161
        },
        {
            "name": "DF Slezak",
            "citations_all": 3847,
            "citations_recent": 2603,
            "h_index_all": 27,
            "h_index_recent": 23,
            "i10_index_all": 48,
            "i10_index_recent": 37
        },
        {
            "name": "G Cecchi",
            "citations_all": 12983,
            "citations_recent": 7354,
            "h_index_all": 53,
            "h_index_recent": 43,
            "i10_index_all": 148,
            "i10_index_recent": 115
        },
        {
            "name": "M Copelli",
            "citations_all": 5497,
            "citations_recent": 3221,
            "h_index_all": 33,
            "h_index_recent": 25,
            "i10_index_all": 69,
            "i10_index_recent": 46
        },
        {
            "name": "S Ribeiro",
            "citations_all": 13829,
            "citations_recent": 7047,
            "h_index_all": 60,
            "h_index_recent": 44,
            "i10_index_all": 133,
            "i10_index_recent": 109
        }
    ],
    "abstract": "Discourse varies with age, education, psychiatric state and historical epoch, but the ontogenetic and cultural dynamics of discourse structure remain to be quantitatively characterized. To this end we investigated word graphs obtained from verbal reports of 200 subjects ages 2-58, and 676 literary texts spanning ~5,000 years. In healthy subjects, lexical diversity, graph size, and long-range recurrence departed from initial near-random levels through a monotonic asymptotic increase across ages, while short-range recurrence showed a corresponding decrease. These changes were explained by education and suggest a hierarchical development of discourse structure: short-range recurrence and lexical diversity stabilize after elementary school, but graph size and long-range recurrence only stabilize after high school. This gradual maturation was blurred in psychotic subjects, who maintained in adulthood a near-random structure. In literature, monotonic asymptotic changes over time were remarkable: While lexical diversity, long-range recurrence and graph size increased away from near-randomness, short-range recurrence declined, from above to below random levels. Bronze Age texts are structurally similar to childish or psychotic discourses, but subsequent texts converge abruptly to the healthy adult pattern around the onset of the Axial Age (800-200 BC), a period of pivotal cultural change. Thus, individually as well as historically, discourse maturation increases the range of word recurrence away from randomness.",
    "published_date": "2016-12-27T00:00:00",
    "last_revised_date": "2016-12-27T00:00:00",
    "num_revisions": 0,
    "pdf_url": "https://arxiv.org/pdf/1612.09268.pdf",
    "primary_category": "Neurons and Cognition (q-bio.NC)",
    "categories": [
        "Neurons and Cognition (q-bio.NC)",
        "Computation and Language (cs.CL)",
        "Physics and Society (physics.soc-ph)"
    ],
    "keywords": null,
    "num_pages": 57,
    "github_stars": null,
    "upvote": 0,
    "citing_models": 0,
    "citing_datasets": 0,
    "citing_spaces": 0,
    "citing_collections": 0,
    "citations_by_year": {
        "2016": 1,
        "2017": 2,
        "2018": 1,
        "2019": 2,
        "2020": 1,
        "2022": 1
    },
    "citationCount": 8,
    "venue": {
        "name": "arXiv.org",
        "type": null,
        "ranking": null
    },
    "citations": [
        {
            "arxiv_id": null,
            "referenceCount": 95,
            "citationCount": 31,
            "influentialCitationCount": null
        },
        {
            "arxiv_id": null,
            "referenceCount": 47,
            "citationCount": 13,
            "influentialCitationCount": null
        },
        {
            "arxiv_id": null,
            "referenceCount": 61,
            "citationCount": 31,
            "influentialCitationCount": null
        },
        {
            "arxiv_id": null,
            "referenceCount": 188,
            "citationCount": 30,
            "influentialCitationCount": null
        },
        {
            "arxiv_id": null,
            "referenceCount": 66,
            "citationCount": 0,
            "influentialCitationCount": null
        },
        {
            "arxiv_id": null,
            "referenceCount": 78,
            "citationCount": 0,
            "influentialCitationCount": null
        }
    ],
    "referenceCount": 72,
    "references": [
        {
            "arxiv_id": null,
            "referenceCount": 0,
            "citationCount": 958,
            "influentialCitationCount": null
        },
        {
            "arxiv_id": null,
            "referenceCount": 26,
            "citationCount": 48,
            "influentialCitationCount": null
        },
        {
            "arxiv_id": null,
            "referenceCount": 44,
            "citationCount": 40,
            "influentialCitationCount": null
        },
        {
            "arxiv_id": null,
            "referenceCount": 126,
            "citationCount": 53,
            "influentialCitationCount": null
        },
        {
            "arxiv_id": null,
            "referenceCount": 147,
            "citationCount": 39,
            "influentialCitationCount": null
        },
        {
            "arxiv_id": null,
            "referenceCount": 35,
            "citationCount": 28,
            "influentialCitationCount": null
        },
        {
            "arxiv_id": null,
            "referenceCount": 147,
            "citationCount": 1630,
            "influentialCitationCount": null
        },
        {
            "arxiv_id": null,
            "referenceCount": 60,
            "citationCount": 132,
            "influentialCitationCount": null
        },
        {
            "arxiv_id": null,
            "referenceCount": 146,
            "citationCount": 448,
            "influentialCitationCount": null
        },
        {
            "arxiv_id": null,
            "referenceCount": 63,
            "citationCount": 140,
            "influentialCitationCount": null
        },
        {
            "arxiv_id": null,
            "referenceCount": 19,
            "citationCount": 9,
            "influentialCitationCount": null
        },
        {
            "arxiv_id": null,
            "referenceCount": 50,
            "citationCount": 293,
            "influentialCitationCount": null
        },
        {
            "arxiv_id": null,
            "referenceCount": 90,
            "citationCount": 368,
            "influentialCitationCount": null
        },
        {
            "arxiv_id": null,
            "referenceCount": 54,
            "citationCount": 576,
            "influentialCitationCount": null
        },
        {
            "arxiv_id": null,
            "referenceCount": 226,
            "citationCount": 273,
            "influentialCitationCount": null
        },
        {
            "arxiv_id": null,
            "referenceCount": 37,
            "citationCount": 233,
            "influentialCitationCount": null
        },
        {
            "arxiv_id": null,
            "referenceCount": 0,
            "citationCount": 1,
            "influentialCitationCount": null
        },
        {
            "arxiv_id": null,
            "referenceCount": 0,
            "citationCount": 877,
            "influentialCitationCount": null
        },
        {
            "arxiv_id": null,
            "referenceCount": 94,
            "citationCount": 352,
            "influentialCitationCount": null
        },
        {
            "arxiv_id": null,
            "referenceCount": 0,
            "citationCount": 205,
            "influentialCitationCount": null
        },
        {
            "arxiv_id": null,
            "referenceCount": 0,
            "citationCount": 86,
            "influentialCitationCount": null
        },
        {
            "arxiv_id": null,
            "referenceCount": 0,
            "citationCount": 172,
            "influentialCitationCount": null
        },
        {
            "arxiv_id": null,
            "referenceCount": 45,
            "citationCount": 405,
            "influentialCitationCount": null
        },
        {
            "arxiv_id": null,
            "referenceCount": 143,
            "citationCount": 273,
            "influentialCitationCount": null
        },
        {
            "arxiv_id": null,
            "referenceCount": 0,
            "citationCount": 160,
            "influentialCitationCount": null
        },
        {
            "arxiv_id": null,
            "referenceCount": 39,
            "citationCount": 61,
            "influentialCitationCount": null
        },
        {
            "arxiv_id": null,
            "referenceCount": 219,
            "citationCount": 536,
            "influentialCitationCount": null
        },
        {
            "arxiv_id": null,
            "referenceCount": 0,
            "citationCount": 39,
            "influentialCitationCount": null
        },
        {
            "arxiv_id": null,
            "referenceCount": 56,
            "citationCount": 92,
            "influentialCitationCount": null
        },
        {
            "arxiv_id": null,
            "referenceCount": 131,
            "citationCount": 899,
            "influentialCitationCount": null
        },
        {
            "arxiv_id": null,
            "referenceCount": 159,
            "citationCount": 11637,
            "influentialCitationCount": null
        },
        {
            "arxiv_id": null,
            "referenceCount": 0,
            "citationCount": 6,
            "influentialCitationCount": null
        },
        {
            "arxiv_id": null,
            "referenceCount": 70,
            "citationCount": 1669,
            "influentialCitationCount": null
        },
        {
            "arxiv_id": null,
            "referenceCount": 72,
            "citationCount": 901,
            "influentialCitationCount": null
        },
        {
            "arxiv_id": null,
            "referenceCount": 148,
            "citationCount": 4259,
            "influentialCitationCount": null
        },
        {
            "arxiv_id": null,
            "referenceCount": 65,
            "citationCount": 1113,
            "influentialCitationCount": null
        },
        {
            "arxiv_id": null,
            "referenceCount": 4,
            "citationCount": 33,
            "influentialCitationCount": null
        },
        {
            "arxiv_id": null,
            "referenceCount": 33,
            "citationCount": 100,
            "influentialCitationCount": null
        },
        {
            "arxiv_id": null,
            "referenceCount": 0,
            "citationCount": 588,
            "influentialCitationCount": null
        },
        {
            "arxiv_id": null,
            "referenceCount": 0,
            "citationCount": 22,
            "influentialCitationCount": null
        },
        {
            "arxiv_id": null,
            "referenceCount": 0,
            "citationCount": 110,
            "influentialCitationCount": null
        },
        {
            "arxiv_id": null,
            "referenceCount": 69,
            "citationCount": 46,
            "influentialCitationCount": null
        },
        {
            "arxiv_id": null,
            "referenceCount": 39,
            "citationCount": 3318,
            "influentialCitationCount": null
        },
        {
            "arxiv_id": null,
            "referenceCount": 1,
            "citationCount": 2201,
            "influentialCitationCount": null
        },
        {
            "arxiv_id": null,
            "referenceCount": 0,
            "citationCount": 168,
            "influentialCitationCount": null
        },
        {
            "arxiv_id": null,
            "referenceCount": 0,
            "citationCount": 140,
            "influentialCitationCount": null
        },
        {
            "arxiv_id": null,
            "referenceCount": 0,
            "citationCount": 14,
            "influentialCitationCount": null
        },
        {
            "arxiv_id": null,
            "referenceCount": 23,
            "citationCount": 2148,
            "influentialCitationCount": null
        },
        {
            "arxiv_id": null,
            "referenceCount": 4,
            "citationCount": 62,
            "influentialCitationCount": null
        },
        {
            "arxiv_id": null,
            "referenceCount": 0,
            "citationCount": 150,
            "influentialCitationCount": null
        },
        {
            "arxiv_id": null,
            "referenceCount": 0,
            "citationCount": 1,
            "influentialCitationCount": null
        },
        {
            "arxiv_id": null,
            "referenceCount": 0,
            "citationCount": 18,
            "influentialCitationCount": null
        },
        {
            "arxiv_id": null,
            "referenceCount": null,
            "citationCount": null,
            "influentialCitationCount": null
        },
        {
            "arxiv_id": null,
            "referenceCount": null,
            "citationCount": null,
            "influentialCitationCount": null
        },
        {
            "arxiv_id": null,
            "referenceCount": null,
            "citationCount": null,
            "influentialCitationCount": null
        },
        {
            "arxiv_id": null,
            "referenceCount": 31,
            "citationCount": 14,
            "influentialCitationCount": null
        },
        {
            "arxiv_id": null,
            "referenceCount": 7,
            "citationCount": 152,
            "influentialCitationCount": null
        },
        {
            "arxiv_id": null,
            "referenceCount": 0,
            "citationCount": 28,
            "influentialCitationCount": null
        },
        {
            "arxiv_id": null,
            "referenceCount": 0,
            "citationCount": 198,
            "influentialCitationCount": null
        },
        {
            "arxiv_id": null,
            "referenceCount": 153,
            "citationCount": 57,
            "influentialCitationCount": null
        },
        {
            "arxiv_id": null,
            "referenceCount": 0,
            "citationCount": 2402,
            "influentialCitationCount": null
        },
        {
            "arxiv_id": null,
            "referenceCount": 0,
            "citationCount": 408,
            "influentialCitationCount": null
        },
        {
            "arxiv_id": null,
            "referenceCount": 0,
            "citationCount": 38,
            "influentialCitationCount": null
        },
        {
            "arxiv_id": null,
            "referenceCount": null,
            "citationCount": null,
            "influentialCitationCount": null
        },
        {
            "arxiv_id": null,
            "referenceCount": 11,
            "citationCount": 8327,
            "influentialCitationCount": null
        },
        {
            "arxiv_id": null,
            "referenceCount": 47,
            "citationCount": 20799,
            "influentialCitationCount": null
        },
        {
            "arxiv_id": null,
            "referenceCount": 0,
            "citationCount": 255,
            "influentialCitationCount": null
        },
        {
            "arxiv_id": null,
            "referenceCount": 0,
            "citationCount": 515,
            "influentialCitationCount": null
        },
        {
            "arxiv_id": null,
            "referenceCount": null,
            "citationCount": null,
            "influentialCitationCount": null
        },
        {
            "arxiv_id": null,
            "referenceCount": 0,
            "citationCount": 733,
            "influentialCitationCount": null
        },
        {
            "arxiv_id": null,
            "referenceCount": null,
            "citationCount": null,
            "influentialCitationCount": null
        },
        {
            "arxiv_id": null,
            "referenceCount": 0,
            "citationCount": 637,
            "influentialCitationCount": null
        }
    ],
    "influentialCitationCount": 1,
    "embedding": null
}