{
    "arxiv_id": "2312.16792",
    "title": "RL-LOGO: Deep Reinforcement Learning Localization for Logo Recognition",
    "authors": [
        {
            "name": "M Fujitake",
            "citations_all": 209,
            "citations_recent": 207,
            "h_index_all": 8,
            "h_index_recent": 8,
            "i10_index_all": 6,
            "i10_index_recent": 6
        }
    ],
    "abstract": "This paper proposes a novel logo image recognition approach incorporating a localization technique based on reinforcement learning. Logo recognition is an image classification task identifying a brand in an image. As the size and position of a logo vary widely from image to image, it is necessary to determine its position for accurate recognition. However, because there is no annotation for the position coordinates, it is impossible to train and infer the location of the logo in the image. Therefore, we propose a deep reinforcement learning localization method for logo recognition (RL-LOGO). It utilizes deep reinforcement learning to identify a logo region in images without annotations of the positions, thereby improving classification accuracy. We demonstrated a significant improvement in accuracy compared with existing methods in several published benchmarks. Specifically, we achieved an 18-point accuracy improvement over competitive methods on the complex dataset Logo-2K+. This demonstrates that the proposed method is a promising approach to logo recognition in real-world applications.",
    "published_date": "2023-12-28T00:00:00",
    "last_revised_date": "2023-12-28T00:00:00",
    "num_revisions": 0,
    "pdf_url": "https://arxiv.org/pdf/2312.16792.pdf",
    "primary_category": "Computer Vision and Pattern Recognition (cs.CV)",
    "categories": [
        "Computer Vision and Pattern Recognition (cs.CV)",
        "Artificial Intelligence (cs.AI)",
        "Machine Learning (cs.LG)",
        "Neural and Evolutionary Computing (cs.NE)"
    ],
    "keywords": null,
    "num_pages": 5,
    "github_stars": null,
    "upvote": 0,
    "citing_models": 0,
    "citing_datasets": 0,
    "citing_spaces": 0,
    "citing_collections": 0,
    "citations_by_year": {
        "2024": 1,
        "2025": 2
    },
    "citationCount": 3,
    "venue": {
        "name": "IEEE International Conference on Acoustics, Speech, and Signal Processing",
        "type": "conference",
        "ranking": "B"
    },
    "citations": [
        {
            "arxiv_id": null,
            "referenceCount": 57,
            "citationCount": 22,
            "influentialCitationCount": null
        },
        {
            "arxiv_id": null,
            "referenceCount": 22,
            "citationCount": 1,
            "influentialCitationCount": null
        },
        {
            "arxiv_id": null,
            "referenceCount": 37,
            "citationCount": 1,
            "influentialCitationCount": null
        }
    ],
    "referenceCount": 19,
    "references": [
        {
            "arxiv_id": null,
            "referenceCount": 68,
            "citationCount": 48,
            "influentialCitationCount": null
        },
        {
            "arxiv_id": null,
            "referenceCount": 32,
            "citationCount": 6,
            "influentialCitationCount": null
        },
        {
            "arxiv_id": null,
            "referenceCount": 26,
            "citationCount": 9,
            "influentialCitationCount": null
        },
        {
            "arxiv_id": null,
            "referenceCount": 122,
            "citationCount": 27,
            "influentialCitationCount": null
        },
        {
            "arxiv_id": null,
            "referenceCount": 30,
            "citationCount": 7,
            "influentialCitationCount": null
        },
        {
            "arxiv_id": null,
            "referenceCount": 66,
            "citationCount": 65,
            "influentialCitationCount": null
        },
        {
            "arxiv_id": null,
            "referenceCount": 34,
            "citationCount": 50,
            "influentialCitationCount": null
        },
        {
            "arxiv_id": null,
            "referenceCount": 79,
            "citationCount": 70,
            "influentialCitationCount": null
        },
        {
            "arxiv_id": null,
            "referenceCount": 41,
            "citationCount": 1459,
            "influentialCitationCount": null
        },
        {
            "arxiv_id": null,
            "referenceCount": 67,
            "citationCount": 44,
            "influentialCitationCount": null
        },
        {
            "arxiv_id": null,
            "referenceCount": 51,
            "citationCount": 455,
            "influentialCitationCount": null
        },
        {
            "arxiv_id": null,
            "referenceCount": 36,
            "citationCount": 52,
            "influentialCitationCount": null
        },
        {
            "arxiv_id": null,
            "referenceCount": 53,
            "citationCount": 203612,
            "influentialCitationCount": null
        },
        {
            "arxiv_id": null,
            "referenceCount": 38,
            "citationCount": 448,
            "influentialCitationCount": null
        },
        {
            "arxiv_id": null,
            "referenceCount": 37,
            "citationCount": 28996,
            "influentialCitationCount": null
        },
        {
            "arxiv_id": null,
            "referenceCount": 43,
            "citationCount": 103199,
            "influentialCitationCount": null
        },
        {
            "arxiv_id": null,
            "referenceCount": 13,
            "citationCount": 266,
            "influentialCitationCount": null
        },
        {
            "arxiv_id": null,
            "referenceCount": 9,
            "citationCount": 191,
            "influentialCitationCount": null
        },
        {
            "arxiv_id": null,
            "referenceCount": 27,
            "citationCount": 66576,
            "influentialCitationCount": null
        }
    ],
    "influentialCitationCount": 0,
    "embedding": null
}