{
    "arxiv_id": "2501.00003",
    "title": "Machine learning models for Si nanoparticle growth in nonthermal plasma",
    "authors": [
        {
            "name": "M Raymond",
            "citations_all": 13,
            "citations_recent": 13,
            "h_index_all": 1,
            "h_index_recent": 1,
            "i10_index_all": 1,
            "i10_index_recent": 1
        },
        {
            "name": "P Elvati",
            "citations_all": 1802,
            "citations_recent": 1281,
            "h_index_all": 19,
            "h_index_recent": 17,
            "i10_index_all": 31,
            "i10_index_recent": 29
        },
        {
            "name": "JC Saldinger",
            "citations_all": 273,
            "citations_recent": 273,
            "h_index_all": 7,
            "h_index_recent": 7,
            "i10_index_all": 6,
            "i10_index_recent": 6
        },
        {
            "name": "J Lin",
            "citations_all": null,
            "citations_recent": null,
            "h_index_all": null,
            "h_index_recent": null,
            "i10_index_all": null,
            "i10_index_recent": null
        },
        {
            "name": "X Shi",
            "citations_all": 374,
            "citations_recent": 260,
            "h_index_all": 10,
            "h_index_recent": 9,
            "i10_index_all": 10,
            "i10_index_recent": 9
        },
        {
            "name": "A Violi",
            "citations_all": 8956,
            "citations_recent": 3583,
            "h_index_all": 55,
            "h_index_recent": 32,
            "i10_index_all": 113,
            "i10_index_recent": 87
        }
    ],
    "abstract": "Nanoparticles (NPs) formed in nonthermal plasmas (NTPs) can have unique properties and applications. However, modeling their growth in these environments presents significant challenges due to the non-equilibrium nature of NTPs, making them computationally expensive to describe. In this work, we address the challenges associated with accelerating the estimation of parameters needed for these models. Specifically, we explore how different machine learning models can be tailored to improve prediction outcomes. We apply these methods to reactive classical molecular dynamics data, which capture the processes associated with colliding silane fragments in NTPs. These reactions exemplify processes where qualitative trends are clear, but their quantification is challenging, hard to generalize, and requires time-consuming simulations. Our results demonstrate that good prediction performance can be achieved when appropriate loss functions are implemented and correct invariances are imposed. While the diversity of molecules used in the training set is critical for accurate prediction, our findings indicate that only a fraction (15-25\\%) of the energy and temperature sampling is required to achieve high levels of accuracy. This suggests a substantial reduction in computational effort is possible for similar systems.",
    "published_date": "2024-10-31T00:00:00",
    "last_revised_date": "2024-10-31T00:00:00",
    "num_revisions": 0,
    "pdf_url": "https://arxiv.org/pdf/2501.00003.pdf",
    "primary_category": "Computational Physics (physics.comp-ph)",
    "categories": [
        "Computational Physics (physics.comp-ph)",
        "Machine Learning (cs.LG)"
    ],
    "keywords": null,
    "num_pages": 26,
    "github_stars": null,
    "upvote": 0,
    "citing_models": 0,
    "citing_datasets": 0,
    "citing_spaces": 0,
    "citing_collections": 0,
    "citations_by_year": {},
    "citationCount": 0,
    "venue": {
        "name": "Plasma Sources Science & Technology",
        "type": "journal",
        "ranking": "Q2"
    },
    "citations": [],
    "referenceCount": 9,
    "references": [
        {
            "arxiv_id": null,
            "referenceCount": 50,
            "citationCount": 655,
            "influentialCitationCount": null
        },
        {
            "arxiv_id": null,
            "referenceCount": 32,
            "citationCount": 11525,
            "influentialCitationCount": null
        },
        {
            "arxiv_id": null,
            "referenceCount": 54,
            "citationCount": 2602,
            "influentialCitationCount": null
        },
        {
            "arxiv_id": null,
            "referenceCount": 17,
            "citationCount": 168,
            "influentialCitationCount": null
        },
        {
            "arxiv_id": null,
            "referenceCount": 10,
            "citationCount": 519,
            "influentialCitationCount": null
        },
        {
            "arxiv_id": null,
            "referenceCount": 93,
            "citationCount": 590,
            "influentialCitationCount": null
        },
        {
            "arxiv_id": null,
            "referenceCount": 72,
            "citationCount": 7,
            "influentialCitationCount": null
        },
        {
            "arxiv_id": null,
            "referenceCount": 0,
            "citationCount": 9118,
            "influentialCitationCount": null
        },
        {
            "arxiv_id": null,
            "referenceCount": null,
            "citationCount": null,
            "influentialCitationCount": null
        }
    ],
    "influentialCitationCount": 0,
    "embedding": null
}